{
  "subscribeKeyboard": [
    [
      {
        "action": {
          "type": "text",
          "payload": "{\"button\": \"1\"}",
          "label": "Подписаться"
        },
        "color": "primary"
      }
    ]
  ],
  "subscribedKeyboard": [
    [
      {
        "action": {
          "type": "text",
          "payload": "{\"button\": \"1\"}",
          "label": "Статус сервисов"
        },
        "color": "primary"
      },
      {
        "action": {
          "type": "text",
          "payload": "{\"button\": \"2\"}",
          "label": "Отписаться"
        },
        "color": "negative"
      }
    ]
  ]
}